README.rst
setup.cfg
setup.py
saucebindings/__init__.py
saucebindings/configs.py
saucebindings/exceptions.py
saucebindings/options.py
saucebindings/session.py
saucebindings.egg-info/PKG-INFO
saucebindings.egg-info/SOURCES.txt
saucebindings.egg-info/dependency_links.txt
saucebindings.egg-info/requires.txt
saucebindings.egg-info/top_level.txt