Metadata-Version: 2.1
Name: saucebindings
Version: 1.3.0
Summary: Sauce Labs Python bindings library
Home-page: https://github.com/saucelabs/sauce_bindings/
Author: josh.grant
Author-email: josh.grant@saucelabs.com
License: MIT
Download-URL: https://github.com/saucelabs/sauce_bindings/archive/v_100.tar.gz
Keywords: Sauce Labs,testing,selenium
Platform: UNKNOWN
Classifier: Development Status :: 4 - Beta
Classifier: Intended Audience :: Developers
Classifier: Topic :: Software Development :: Testing
Classifier: License :: OSI Approved :: MIT License
Classifier: Programming Language :: Python :: 3
Classifier: Programming Language :: Python :: 3.5
Classifier: Programming Language :: Python :: 3.6
